cc_faice/__init__.py
cc_faice/__main__.py
cc_faice/agent/__init__.py
cc_faice/agent/__main__.py
cc_faice/agent/main.py
cc_faice/commons/__init__.py
cc_faice/commons/docker.py
cc_faice/commons/templates.py
cc_faice/convert/__init__.py
cc_faice/convert/__main__.py
cc_faice/convert/batches/__init__.py
cc_faice/convert/batches/__main__.py
cc_faice/convert/batches/main.py
cc_faice/convert/cwl/__init__.py
cc_faice/convert/cwl/__main__.py
cc_faice/convert/cwl/main.py
cc_faice/convert/format/__init__.py
cc_faice/convert/format/__main__.py
cc_faice/convert/format/main.py
cc_faice/convert/main.py
cc_faice/exec/__init__.py
cc_faice/exec/__main__.py
cc_faice/exec/main.py
cc_faice/execution_engine/__init__.py
cc_faice/execution_engine/red_execution_engine.py
cc_faice/main.py
cc_faice/schema/__init__.py
cc_faice/schema/__main__.py
cc_faice/schema/list/__init__.py
cc_faice/schema/list/__main__.py
cc_faice/schema/list/main.py
cc_faice/schema/main.py
cc_faice/schema/show/__init__.py
cc_faice/schema/show/__main__.py
cc_faice/schema/show/main.py
cc_faice/schema/validate/__init__.py
cc_faice/schema/validate/__main__.py
cc_faice/schema/validate/main.py
cc_faice/version.py
cc_faice-9.3.0.dist-info/LICENSE
cc_faice-9.3.0.dist-info/METADATA
cc_faice-9.3.0.dist-info/WHEEL
cc_faice-9.3.0.dist-info/entry_points.txt
cc_faice-9.3.0.dist-info/RECORD
