Metadata-Version: 2.1
Name: cc-faice
Version: 9.3.0
Summary: FAICE (Fair Collaboration and Experiments) is part of the Curious Containers project. It enables researchers to perform and distribute reproducible data-driven experiments defined in the RED format.
Home-page: https://www.curious-containers.cc/
License: AGPL-3.0
Author: Christoph Jansen
Author-email: Christoph.Jansen@htw-berlin.de
Requires-Python: >=3.7,<4.0
Classifier: License :: OSI Approved :: GNU Affero General Public License v3
Classifier: Programming Language :: Python :: 3
Classifier: Programming Language :: Python :: 3.7
Classifier: Programming Language :: Python :: 3.8
Classifier: Programming Language :: Python :: 3.9
Classifier: Programming Language :: Python :: 3.10
Classifier: Programming Language :: Python :: 3.11
Requires-Dist: cc-core (>=9.3,<9.4)
Requires-Dist: red-fill (>=9.3,<9.4)
Requires-Dist: urllib3 (>=1.26,<2.0)
Project-URL: Repository, https://github.com/curious-containers/curious-containers
